ivoryos_mcp/server.py
ivoryos_mcp-0.1.7.dist-info/licenses/LICENSE
ivoryos_mcp-0.1.7.dist-info/METADATA
ivoryos_mcp-0.1.7.dist-info/WHEEL
ivoryos_mcp-0.1.7.dist-info/entry_points.txt
ivoryos_mcp-0.1.7.dist-info/top_level.txt
ivoryos_mcp-0.1.7.dist-info/RECORD
