Metadata-Version: 2.4
Name: ivoryos-mcp
Version: 0.1.7
Summary: MCP server for ivoryOS. 
Project-URL: Homepage, https://gitlab.com/heingroup/ivoryos-suite/ivoryos-mcp
Requires-Python: >=3.10
License-File: LICENSE
Requires-Dist: mcp[cli]>=1.9.2
Requires-Dist: ivoryos-client==0.2.9
Requires-Dist: python-dotenv
Dynamic: license-file
